fw_gear_nnunetv1/__init__.py
fw_gear_nnunetv1/main.py
fw_gear_nnunetv1/parser.py
fw_gear_nnunetv1/utils.py
fw_gear_nnunetv1-0.1.2.dist-info/METADATA
fw_gear_nnunetv1-0.1.2.dist-info/WHEEL
fw_gear_nnunetv1-0.1.2.dist-info/RECORD
