Metadata-Version: 2.1
Name: fw-gear-nnunetv1
Version: 0.1.2
Summary: Run inference by the nnUnet v1 model.
Home-page: https://gitlab.com/flywheel-io/scientific-solutions/clients/regeneron/nnunetv1
License: The nnUnet source code is under an [Apache License 2.0](https://github.com/MIC-DKFZ/nnUNet/blob/nnunetv1/LICENSE); the remainder of this gear is under [MIT License](https://gitlab.com/flywheel-io/scientific-solutions/gears/templates/skeleton/-/blob/76f2c943ad5212380e39b27a756574bce94a3782/LICENSE).
Keywords: Flywheel,Gears
Author: Flywheel
Author-email: support@flywheel.io
Requires-Python: >=3.9,<4.0
Classifier: License :: Other/Proprietary License
Classifier: Programming Language :: Python :: 3
Classifier: Programming Language :: Python :: 3.9
Classifier: Programming Language :: Python :: 3.10
Classifier: Programming Language :: Python :: 3.11
Classifier: Programming Language :: Python :: 3.12
Classifier: Topic :: Scientific/Engineering
Requires-Dist: flywheel-gear-toolkit (>=0.6,<0.7)
Requires-Dist: flywheel-sdk (>=18,<19)
Project-URL: Repository, https://gitlab.com/flywheel-io/scientific-solutions/clients/regeneron/nnunetv1
